rmw_implementation/_dummy.cpython-310-x86_64-linux-gnu.so
ros_rmw_implementation-3.0.4.data/data/share/ament_index/resource_index/package_run_dependencies/rmw_implementation
ros_rmw_implementation-3.0.4.data/data/share/ament_index/resource_index/packages/rmw_implementation
ros_rmw_implementation-3.0.4.data/data/share/ament_index/resource_index/parent_prefix_path/rmw_implementation
ros_rmw_implementation-3.0.4.data/data/share/ament_index/resource_index/rmw_typesupport/rmw_implementation
ros_rmw_implementation-3.0.4.data/data/share/ament_index/resource_index/rmw_typesupport_c/rmw_implementation
ros_rmw_implementation-3.0.4.data/data/share/ament_index/resource_index/rmw_typesupport_cpp/rmw_implementation
ros_rmw_implementation-3.0.4.data/data/share/rmw_implementation/local_setup.bash
ros_rmw_implementation-3.0.4.data/data/share/rmw_implementation/local_setup.dsv
ros_rmw_implementation-3.0.4.data/data/share/rmw_implementation/local_setup.sh
ros_rmw_implementation-3.0.4.data/data/share/rmw_implementation/local_setup.zsh
ros_rmw_implementation-3.0.4.data/data/share/rmw_implementation/package.dsv
ros_rmw_implementation-3.0.4.data/data/share/rmw_implementation/package.xml
ros_rmw_implementation-3.0.4.data/data/share/rmw_implementation/cmake/rmw_implementation-extras.cmake
ros_rmw_implementation-3.0.4.data/data/share/rmw_implementation/cmake/rmw_implementationConfig-version.cmake
ros_rmw_implementation-3.0.4.data/data/share/rmw_implementation/cmake/rmw_implementationConfig.cmake
ros_rmw_implementation-3.0.4.data/data/share/rmw_implementation/environment/ament_prefix_path.dsv
ros_rmw_implementation-3.0.4.data/data/share/rmw_implementation/environment/ament_prefix_path.sh
ros_rmw_implementation-3.0.4.data/data/share/rmw_implementation/environment/path.dsv
ros_rmw_implementation-3.0.4.data/data/share/rmw_implementation/environment/path.sh
ros_rmw_implementation-3.0.4.dist-info/METADATA
ros_rmw_implementation-3.0.4.dist-info/WHEEL
ros_rmw_implementation-3.0.4.dist-info/top_level.txt
ros_rmw_implementation-3.0.4.dist-info/RECORD
