Metadata-Version: 2.4
Name: ros-rmw-implementation
Version: 3.0.4
Summary: A ROS 2 package providing a proxy implementation for the Middleware Interface (RMW), dynamically forwarding calls to the selected RMW implementation.
Requires-Dist: ros-rcpputils~=2.13.5
Requires-Dist: ros-ament-index-cpp~=1.11.0
Requires-Dist: ros-rmw-implementation-cmake~=7.8.2
Requires-Dist: ros-rcutils~=6.9.8
Dynamic: description
Dynamic: description-content-type
Dynamic: requires-dist
Dynamic: summary
